LICENSE.txt
MANIFEST.in
README.rst
setup.cfg
setup.py
pypirc3/__init__.py
pypirc3/client.py
pypirc3/option.py
pypirc3/pypirc.py
pypirc3.egg-info/PKG-INFO
pypirc3.egg-info/SOURCES.txt
pypirc3.egg-info/dependency_links.txt
pypirc3.egg-info/entry_points.txt
pypirc3.egg-info/requires.txt
pypirc3.egg-info/top_level.txt
pypirc3/executor/__init__.py
pypirc3/executor/creator.py
pypirc3/executor/viewer.py
tests/executor/__init__.py
tests/executor/test_creator.py
tests/executor/test_viewer.py