Metadata-Version: 1.1
Name: pypirc3
Version: 1.1.0
Summary: command line tool to show and create .pypirc with Python 3
Home-page: https://github.com/shirakiya/pypirc3
Author: shirakiya
Author-email: shirakiya.pv@gmail.com
License: MIT
Keywords: pypi pypirc cli setup
Platform: UNKNOWN
Classifier: Development Status :: 5 - Production/Stable
Classifier: Intended Audience :: Developers
Classifier: Topic :: Utilities
Classifier: License :: OSI Approved :: MIT License
Classifier: Programming Language :: Python :: 3.2
Classifier: Programming Language :: Python :: 3.3
Classifier: Programming Language :: Python :: 3.4
Classifier: Programming Language :: Python :: 3.5
